    [
    {
        "name":"VERI",
        "fullName":"Veritaseum",
        "bid":"Bid 0.043005730",
        "ask":"Ask 0.046400000",
        "decimal":"0.0820000020",
        "daily":"21.705 = Daily"
    },
    {
        "name":"SXDT",
        "fullName":"Spectre.ai D-Token",
        "bid":"Bid 0.043005730",
        "ask":"Ask 0.046400000",
        "decimal":"0.0820000020",
        "daily":"21.705 = Daily"
    },
    {
        "name":"PPT",
        "fullName":"Populous Platform",
        "bid":"Bid 0.043005730",
        "ask":"Ask 0.046400000",
        "decimal":"0.0820000020",
        "daily":"21.705 = Daily"
    },
    {
        "name":"PPP",
        "fullName":"Paypie",
        "bid":"Bid 0.043005730",
        "ask":"Ask 0.046400000",
        "decimal":"0.0820000020",
        "daily":"21.705 = Daily"
    },
    {
        "name":"A",
        "fullName":"Alpha",
        "bid":"Bid 0.043005730",
        "ask":"Ask 0.046400000",
        "decimal":"0.0820000020",
        "daily":"21.705 = Daily"
    },
    {
        "name":"DATA",
        "fullName":"DATAcoin",
        "bid":"Bid 0.043005730",
        "ask":"Ask 0.046400000",
        "decimal":"0.0820000020",
        "daily":"21.705 = Daily"
    },
    {
        "name":"VERI",
        "fullName":"Veritaseum",
        "bid":"Bid 0.043005730",
        "ask":"Ask 0.046400000",
        "decimal":"0.0820000020",
        "daily":"21.705 = Daily"
    },
    {
        "name":"VERI",
        "fullName":"Veritaseum",
        "bid":"Bid 0.043005730",
        "ask":"Ask 0.046400000",
        "decimal":"0.0820000020",
        "daily":"21.705 = Daily"
    },
    {
        "name":"VERI",
        "fullName":"Veritaseum",
        "bid":"Bid 0.043005730",
        "ask":"Ask 0.046400000",
        "decimal":"0.0820000020",
        "daily":"21.705 = Daily"
    }

]
 